eversa
